IDG/__init__.py
IDG/deployment.py
IDG/jsonObject.py
IDG/module.py
IDG/routeSettings.py
IDG/exceptions/DotInNameException.py
IDG/exceptions/IDGException.py
IDG/exceptions/__init__.py
IoT_Deployment_Generator-0.0.14.dist-info/LICENSE
IoT_Deployment_Generator-0.0.14.dist-info/METADATA
IoT_Deployment_Generator-0.0.14.dist-info/WHEEL
IoT_Deployment_Generator-0.0.14.dist-info/top_level.txt
IoT_Deployment_Generator-0.0.14.dist-info/RECORD
