Metadata-Version: 2.1
Name: IoT-Deployment-Generator
Version: 0.0.14
Summary: Library used to create Azure IoT Edge deployment templates with python code 
Home-page: https://github.com/shoter/IotDeploymentGenerator
Author: Shoter
License: MIT License
Keywords: iot edge azure
Platform: any
Classifier: License :: OSI Approved :: MIT License
Classifier: Operating System :: OS Independent
Classifier: Programming Language :: Python :: 3
License-File: LICENSE
